{"nodes":[{"id":"src_tui_text_rs","label":"text","source_file":"./src/tui/text.rs","node_type":"file"},{"id":"src_tui_text_rs_truncate_str","label":"truncate_str()","source_file":"./src/tui/text.rs","source_location":"L2","node_type":"function"},{"id":"src_tui_text_rs_import_super","label":"super::*","source_file":"./src/tui/text.rs","source_location":"L14","node_type":"module"},{"id":"src_tui_text_rs_truncate_respects_char_boundaries","label":"truncate_respects_char_boundaries()","source_file":"./src/tui/text.rs","source_location":"L17","node_type":"function"}],"edges":[{"source":"src_tui_text_rs","target":"src_tui_text_rs_truncate_str","relation":"defines","confidence":"EXTRACTED","confidence_score":1.0,"source_file":"./src/tui/text.rs","source_location":"L2","weight":1.0,"provenance":"ast:defines"},{"source":"src_tui_text_rs","target":"src_tui_text_rs_import_super","relation":"imports","confidence":"EXTRACTED","confidence_score":1.0,"source_file":"./src/tui/text.rs","source_location":"L14","weight":1.0,"provenance":"ast:import","imported_symbols":["*"]},{"source":"src_tui_text_rs","target":"src_tui_text_rs_truncate_respects_char_boundaries","relation":"defines","confidence":"EXTRACTED","confidence_score":1.0,"source_file":"./src/tui/text.rs","source_location":"L17","weight":1.0,"provenance":"ast:defines"},{"source":"src_tui_text_rs_truncate_respects_char_boundaries","target":"src_tui_text_rs_truncate_str","relation":"calls","confidence":"INFERRED","confidence_score":0.7,"source_file":"./src/tui/text.rs","weight":1.0,"provenance":"ast:call-resolve"}],"hyperedges":[]}