{"nodes":[{"id":"tests_calldata_parity_rs","label":"calldata_parity","source_file":"./tests/calldata_parity.rs","node_type":"file"},{"id":"tests_calldata_parity_rs_import_std_str_fromstr","label":"std::str::FromStr","source_file":"./tests/calldata_parity.rs","source_location":"L5","node_type":"module"},{"id":"tests_calldata_parity_rs_import_alloy_hex","label":"alloy::hex","source_file":"./tests/calldata_parity.rs","source_location":"L7","node_type":"module"},{"id":"tests_calldata_parity_rs_import_alloy_primitives_address_bytes_fixedbytes_u256","label":"alloy::primitives::{Address, Bytes, FixedBytes, U256}","source_file":"./tests/calldata_parity.rs","source_location":"L8","node_type":"module"},{"id":"tests_calldata_parity_rs_import_rpbot_abis_executorcall","label":"rpbot::abis::ExecutorCall","source_file":"./tests/calldata_parity.rs","source_location":"L9","node_type":"module"},{"id":"tests_calldata_parity_rs_import_rpbot_core_types_edge_poolstate_protocoltype_v3poolstate_v4poolstate","label":"rpbot::core::types::{Edge, PoolState, ProtocolType, V3PoolState, V4PoolState}","source_file":"./tests/calldata_parity.rs","source_location":"L10","node_type":"module"},{"id":"tests_calldata_parity_rs_import_rpbot_pipeline_arena_statearena","label":"rpbot::pipeline::arena::StateArena","source_file":"./tests/calldata_parity.rs","source_location":"L11","node_type":"module"},{"id":"tests_calldata_parity_rs_import_rpbot_pipeline_types_poolmeta","label":"rpbot::pipeline::types::PoolMeta","source_file":"./tests/calldata_parity.rs","source_location":"L12","node_type":"module"},{"id":"tests_calldata_parity_rs_import_rpbot_services_execution_calldata_routeencodeconfig_build_arb_calldata_build_calldata_hops_compute_route_hash_encode_route","label":"rpbot::services::execution::calldata::{\n    RouteEncodeConfig, build_arb_calldata, build_calldata_hops, compute_route_hash, encode_route,\n}","source_file":"./tests/calldata_parity.rs","source_location":"L13","node_type":"module"},{"id":"tests_calldata_parity_rs_addr","label":"addr()","source_file":"./tests/calldata_parity.rs","source_location":"L20","node_type":"function"},{"id":"tests_calldata_parity_rs_fixture_reserve","label":"fixture_reserve()","source_file":"./tests/calldata_parity.rs","source_location":"L24","node_type":"function"},{"id":"tests_calldata_parity_rs_register_v2_pool","label":"register_v2_pool()","source_file":"./tests/calldata_parity.rs","source_location":"L28","node_type":"function"},{"id":"tests_calldata_parity_rs_test_encode_cfg","label":"test_encode_cfg()","source_file":"./tests/calldata_parity.rs","source_location":"L40","node_type":"function"},{"id":"tests_calldata_parity_rs_route_hash_matches_ts_simple_fixture","label":"route_hash_matches_ts_simple_fixture()","source_file":"./tests/calldata_parity.rs","source_location":"L48","node_type":"function"},{"id":"tests_calldata_parity_rs_multi_hop_v2_matches_ts_fixture","label":"multi_hop_v2_matches_ts_fixture()","source_file":"./tests/calldata_parity.rs","source_location":"L70","node_type":"function"},{"id":"tests_calldata_parity_rs_execute_arb_wrapper_matches_ts_fixture","label":"execute_arb_wrapper_matches_ts_fixture()","source_file":"./tests/calldata_parity.rs","source_location":"L148","node_type":"function"},{"id":"tests_calldata_parity_rs_v4_single_hop_matches_ts_fixture","label":"v4_single_hop_matches_ts_fixture()","source_file":"./tests/calldata_parity.rs","source_location":"L185","node_type":"function"},{"id":"tests_calldata_parity_rs_kyber_single_hop_matches_ts_fixture","label":"kyber_single_hop_matches_ts_fixture()","source_file":"./tests/calldata_parity.rs","source_location":"L247","node_type":"function"}],"edges":[{"source":"tests_calldata_parity_rs","target":"tests_calldata_parity_rs_import_std_str_fromstr","relation":"imports","confidence":"EXTRACTED","confidence_score":1.0,"source_file":"./tests/calldata_parity.rs","source_location":"L5","weight":1.0,"provenance":"ast:import","imported_symbols":["FromStr"]},{"source":"tests_calldata_parity_rs","target":"tests_calldata_parity_rs_import_alloy_hex","relation":"imports","confidence":"EXTRACTED","confidence_score":1.0,"source_file":"./tests/calldata_parity.rs","source_location":"L7","weight":1.0,"provenance":"ast:import","imported_symbols":["hex"]},{"source":"tests_calldata_parity_rs","target":"tests_calldata_parity_rs_import_alloy_primitives_address_bytes_fixedbytes_u256","relation":"imports","confidence":"EXTRACTED","confidence_score":1.0,"source_file":"./tests/calldata_parity.rs","source_location":"L8","weight":1.0,"provenance":"ast:import","imported_symbols":["{Address, Bytes, FixedBytes, U256}"]},{"source":"tests_calldata_parity_rs","target":"tests_calldata_parity_rs_import_rpbot_abis_executorcall","relation":"imports","confidence":"EXTRACTED","confidence_score":1.0,"source_file":"./tests/calldata_parity.rs","source_location":"L9","weight":1.0,"provenance":"ast:import","imported_symbols":["ExecutorCall"]},{"source":"tests_calldata_parity_rs","target":"tests_calldata_parity_rs_import_rpbot_core_types_edge_poolstate_protocoltype_v3poolstate_v4poolstate","relation":"imports","confidence":"EXTRACTED","confidence_score":1.0,"source_file":"./tests/calldata_parity.rs","source_location":"L10","weight":1.0,"provenance":"ast:import","imported_symbols":["{Edge, PoolState, ProtocolType, V3PoolState, V4PoolState}"]},{"source":"tests_calldata_parity_rs","target":"tests_calldata_parity_rs_import_rpbot_pipeline_arena_statearena","relation":"imports","confidence":"EXTRACTED","confidence_score":1.0,"source_file":"./tests/calldata_parity.rs","source_location":"L11","weight":1.0,"provenance":"ast:import","imported_symbols":["StateArena"]},{"source":"tests_calldata_parity_rs","target":"tests_calldata_parity_rs_import_rpbot_pipeline_types_poolmeta","relation":"imports","confidence":"EXTRACTED","confidence_score":1.0,"source_file":"./tests/calldata_parity.rs","source_location":"L12","weight":1.0,"provenance":"ast:import","imported_symbols":["PoolMeta"]},{"source":"tests_calldata_parity_rs","target":"tests_calldata_parity_rs_import_rpbot_services_execution_calldata_routeencodeconfig_build_arb_calldata_build_calldata_hops_compute_route_hash_encode_route","relation":"imports","confidence":"EXTRACTED","confidence_score":1.0,"source_file":"./tests/calldata_parity.rs","source_location":"L13","weight":1.0,"provenance":"ast:import","imported_symbols":["{\n    RouteEncodeConfig, build_arb_calldata, build_calldata_hops, compute_route_hash, encode_route,\n}"]},{"source":"tests_calldata_parity_rs","target":"tests_calldata_parity_rs_addr","relation":"defines","confidence":"EXTRACTED","confidence_score":1.0,"source_file":"./tests/calldata_parity.rs","source_location":"L20","weight":1.0,"provenance":"ast:defines"},{"source":"tests_calldata_parity_rs","target":"tests_calldata_parity_rs_fixture_reserve","relation":"defines","confidence":"EXTRACTED","confidence_score":1.0,"source_file":"./tests/calldata_parity.rs","source_location":"L24","weight":1.0,"provenance":"ast:defines"},{"source":"tests_calldata_parity_rs","target":"tests_calldata_parity_rs_register_v2_pool","relation":"defines","confidence":"EXTRACTED","confidence_score":1.0,"source_file":"./tests/calldata_parity.rs","source_location":"L28","weight":1.0,"provenance":"ast:defines"},{"source":"tests_calldata_parity_rs","target":"tests_calldata_parity_rs_test_encode_cfg","relation":"defines","confidence":"EXTRACTED","confidence_score":1.0,"source_file":"./tests/calldata_parity.rs","source_location":"L40","weight":1.0,"provenance":"ast:defines"},{"source":"tests_calldata_parity_rs","target":"tests_calldata_parity_rs_route_hash_matches_ts_simple_fixture","relation":"defines","confidence":"EXTRACTED","confidence_score":1.0,"source_file":"./tests/calldata_parity.rs","source_location":"L48","weight":1.0,"provenance":"ast:defines"},{"source":"tests_calldata_parity_rs","target":"tests_calldata_parity_rs_multi_hop_v2_matches_ts_fixture","relation":"defines","confidence":"EXTRACTED","confidence_score":1.0,"source_file":"./tests/calldata_parity.rs","source_location":"L70","weight":1.0,"provenance":"ast:defines"},{"source":"tests_calldata_parity_rs","target":"tests_calldata_parity_rs_execute_arb_wrapper_matches_ts_fixture","relation":"defines","confidence":"EXTRACTED","confidence_score":1.0,"source_file":"./tests/calldata_parity.rs","source_location":"L148","weight":1.0,"provenance":"ast:defines"},{"source":"tests_calldata_parity_rs","target":"tests_calldata_parity_rs_v4_single_hop_matches_ts_fixture","relation":"defines","confidence":"EXTRACTED","confidence_score":1.0,"source_file":"./tests/calldata_parity.rs","source_location":"L185","weight":1.0,"provenance":"ast:defines"},{"source":"tests_calldata_parity_rs","target":"tests_calldata_parity_rs_kyber_single_hop_matches_ts_fixture","relation":"defines","confidence":"EXTRACTED","confidence_score":1.0,"source_file":"./tests/calldata_parity.rs","source_location":"L247","weight":1.0,"provenance":"ast:defines"},{"source":"tests_calldata_parity_rs_register_v2_pool","target":"tests_calldata_parity_rs_fixture_reserve","relation":"calls","confidence":"INFERRED","confidence_score":0.7,"source_file":"./tests/calldata_parity.rs","weight":1.0,"provenance":"ast:call-resolve"},{"source":"tests_calldata_parity_rs_multi_hop_v2_matches_ts_fixture","target":"tests_calldata_parity_rs_addr","relation":"calls","confidence":"INFERRED","confidence_score":0.7,"source_file":"./tests/calldata_parity.rs","weight":1.0,"provenance":"ast:call-resolve"},{"source":"tests_calldata_parity_rs_multi_hop_v2_matches_ts_fixture","target":"tests_calldata_parity_rs_register_v2_pool","relation":"calls","confidence":"INFERRED","confidence_score":0.7,"source_file":"./tests/calldata_parity.rs","weight":1.0,"provenance":"ast:call-resolve"},{"source":"tests_calldata_parity_rs_execute_arb_wrapper_matches_ts_fixture","target":"tests_calldata_parity_rs_addr","relation":"calls","confidence":"INFERRED","confidence_score":0.7,"source_file":"./tests/calldata_parity.rs","weight":1.0,"provenance":"ast:call-resolve"},{"source":"tests_calldata_parity_rs_v4_single_hop_matches_ts_fixture","target":"tests_calldata_parity_rs_addr","relation":"calls","confidence":"INFERRED","confidence_score":0.7,"source_file":"./tests/calldata_parity.rs","weight":1.0,"provenance":"ast:call-resolve"},{"source":"tests_calldata_parity_rs_v4_single_hop_matches_ts_fixture","target":"tests_calldata_parity_rs_test_encode_cfg","relation":"calls","confidence":"INFERRED","confidence_score":0.7,"source_file":"./tests/calldata_parity.rs","weight":1.0,"provenance":"ast:call-resolve"},{"source":"tests_calldata_parity_rs_kyber_single_hop_matches_ts_fixture","target":"tests_calldata_parity_rs_addr","relation":"calls","confidence":"INFERRED","confidence_score":0.7,"source_file":"./tests/calldata_parity.rs","weight":1.0,"provenance":"ast:call-resolve"},{"source":"tests_calldata_parity_rs_kyber_single_hop_matches_ts_fixture","target":"tests_calldata_parity_rs_test_encode_cfg","relation":"calls","confidence":"INFERRED","confidence_score":0.7,"source_file":"./tests/calldata_parity.rs","weight":1.0,"provenance":"ast:call-resolve"}],"hyperedges":[]}